zx_rpa/__init__.py
zx_rpa/feishu_api.py
zx_rpa/photoshop_api.py
zx_rpa-1.0.1.dist-info/METADATA
zx_rpa-1.0.1.dist-info/WHEEL
zx_rpa-1.0.1.dist-info/top_level.txt
zx_rpa-1.0.1.dist-info/RECORD
