Metadata-Version: 2.2
Name: zx_rpa
Version: 1.0.1
Summary: a ligh weight menu , support both win and mac 
Author: zang xin
Author-email: zangxincz@gmail.com
Requires-Python: >=3.12
Requires-Dist: requests
Dynamic: author
Dynamic: author-email
Dynamic: description
Dynamic: description-content-type
Dynamic: requires-dist
Dynamic: requires-python
Dynamic: summary
